README.rst
setup.py
pmxbot_haiku/__init__.py
pmxbot_haiku/haiku.py
pmxbot_haiku/models.py
pmxbot_haiku.egg-info/PKG-INFO
pmxbot_haiku.egg-info/SOURCES.txt
pmxbot_haiku.egg-info/dependency_links.txt
pmxbot_haiku.egg-info/entry_points.txt
pmxbot_haiku.egg-info/not-zip-safe
pmxbot_haiku.egg-info/top_level.txt